background.py
background-0.2.1.dist-info/METADATA
background-0.2.1.dist-info/WHEEL
background-0.2.1.dist-info/top_level.txt
background-0.2.1.dist-info/RECORD
